{
  "name": "cage_5",
  "tags": [],
  "folder": "patterns/CNAP-81",
  "cna_sequence": [
    [
      0,
      0,
      0
    ],
    [
      1,
      0,
      0
    ],
    [
      2,
      0,
      0
    ]
  ],
  "frequencies": [
    1,
    2,
    1
  ],
  "coordination": 4,
  "description": "",
  "additional_notes": "",
  "counts": {
    "D2(Glo, Au310)-glo000": 1,
    "D3(Melted_new, Cu)-Cu586_melt1200": 1,
    "D3(Melted_new, Cu)-Cu561_melt1200": 1,
    "D3(Melted_new, Al)-Al-melted": 1,
    "D3(Melted_new_new, Al)-Al-melted": 1,
    "D3(Melted_new_new, Al)-traj.stair.cool.923.1947": 2
  },
  "id": "CNAP-81"
}